manga_updates_api_client/__init__.py
manga_updates_api_client/api/__init__.py
manga_updates_api_client/api/aboutus/__init__.py
manga_updates_api_client/api/aboutus/add_aboutus_category.py
manga_updates_api_client/api/aboutus/add_aboutus_category_user.py
manga_updates_api_client/api/aboutus/delete_aboutus_category.py
manga_updates_api_client/api/aboutus/delete_aboutus_category_user.py
manga_updates_api_client/api/aboutus/reorder_aboutus.py
manga_updates_api_client/api/aboutus/retrieve_aboutus_categories_and_users.py
manga_updates_api_client/api/aboutus/retrieve_aboutus_category.py
manga_updates_api_client/api/aboutus/retrieve_aboutus_description.py
manga_updates_api_client/api/aboutus/update_aboutus_category.py
manga_updates_api_client/api/aboutus/update_aboutus_description.py
manga_updates_api_client/api/account/__init__.py
manga_updates_api_client/api/account/captcha.py
manga_updates_api_client/api/account/confirm_and_change_password.py
manga_updates_api_client/api/account/confirm_delete_account.py
manga_updates_api_client/api/account/confirm_registration.py
manga_updates_api_client/api/account/delete_account.py
manga_updates_api_client/api/account/forgot_password.py
manga_updates_api_client/api/account/login.py
manga_updates_api_client/api/account/logout.py
manga_updates_api_client/api/account/profile.py
manga_updates_api_client/api/account/register_member.py
manga_updates_api_client/api/account/resend_auth_email.py
manga_updates_api_client/api/account/send_forgot_email.py
manga_updates_api_client/api/authors/__init__.py
manga_updates_api_client/api/authors/add_author.py
manga_updates_api_client/api/authors/delete_author.py
manga_updates_api_client/api/authors/delete_image.py
manga_updates_api_client/api/authors/lock_author_field.py
manga_updates_api_client/api/authors/retrieve_author.py
manga_updates_api_client/api/authors/retrieve_author_locks.py
manga_updates_api_client/api/authors/retrieve_author_series.py
manga_updates_api_client-1.0.0.dist-info/WHEEL
manga_updates_api_client-1.0.0.dist-info/METADATA
manga_updates_api_client-1.0.0.dist-info/RECORD
